LICENSE
MANIFEST.in
README.md
setup.cfg
setup.py
bin/recover_scrabble_game
scrabble/__init__.py
scrabble/config.py
scrabble/dictionary.json
scrabble/helpers.py
scrabble/main.py
scrabble.egg-info/PKG-INFO
scrabble.egg-info/SOURCES.txt
scrabble.egg-info/dependency_links.txt
scrabble.egg-info/not-zip-safe
scrabble.egg-info/top_level.txt