Metadata-Version: 1.0
Name: scrabble
Version: 1.2
Summary: Scrabble game with move recovery and best move analysis
Home-page: https://github.com/benjamincrom/scrabble
Author: Benjamin B. Crom
Author-email: benjamincrom@gmail.com
License: MIT
Platform: UNKNOWN
